kuavo_humanoid_sdk/__init__.py
kuavo_humanoid_sdk/common/launch_robot_tool.py
kuavo_humanoid_sdk/common/logger.py
kuavo_humanoid_sdk/common/websocket_kuavo_sdk.py
kuavo_humanoid_sdk/interfaces/__init__.py
kuavo_humanoid_sdk/interfaces/data_types.py
kuavo_humanoid_sdk/interfaces/end_effector.py
kuavo_humanoid_sdk/interfaces/robot.py
kuavo_humanoid_sdk/interfaces/robot_info.py
kuavo_humanoid_sdk/kuavo/__init__.py
kuavo_humanoid_sdk/kuavo/dexterous_hand.py
kuavo_humanoid_sdk/kuavo/leju_claw.py
kuavo_humanoid_sdk/kuavo/robot.py
kuavo_humanoid_sdk/kuavo/robot_arm.py
kuavo_humanoid_sdk/kuavo/robot_audio.py
kuavo_humanoid_sdk/kuavo/robot_head.py
kuavo_humanoid_sdk/kuavo/robot_info.py
kuavo_humanoid_sdk/kuavo/robot_observation.py
kuavo_humanoid_sdk/kuavo/robot_state.py
kuavo_humanoid_sdk/kuavo/robot_tool.py
kuavo_humanoid_sdk/kuavo/robot_vision.py
kuavo_humanoid_sdk/kuavo/core/audio.py
kuavo_humanoid_sdk/kuavo/core/core.py
kuavo_humanoid_sdk/kuavo/core/dex_hand_control.py
kuavo_humanoid_sdk/kuavo/core/leju_claw_control.py
kuavo_humanoid_sdk/kuavo/core/ros_env.py
kuavo_humanoid_sdk/kuavo/core/ros/audio.py
kuavo_humanoid_sdk/kuavo/core/ros/control.py
kuavo_humanoid_sdk/kuavo/core/ros/observation.py
kuavo_humanoid_sdk/kuavo/core/ros/param.py
kuavo_humanoid_sdk/kuavo/core/ros/sat_utils.py
kuavo_humanoid_sdk/kuavo/core/ros/state.py
kuavo_humanoid_sdk/kuavo/core/ros/tools.py
kuavo_humanoid_sdk/kuavo/core/ros/vision.py
kuavo_humanoid_sdk/kuavo_strategy/__init__.py
kuavo_humanoid_sdk/kuavo_strategy/kuavo_strategy.py
kuavo_humanoid_sdk/kuavo_strategy/grasp_box/grasp_box_strategy.py
kuavo_humanoid_sdk/msg/__init__.py
kuavo_humanoid_sdk_ws-1.3.1.dist-info/METADATA
kuavo_humanoid_sdk_ws-1.3.1.dist-info/WHEEL
kuavo_humanoid_sdk_ws-1.3.1.dist-info/top_level.txt
kuavo_humanoid_sdk_ws-1.3.1.dist-info/RECORD
