Metadata-Version: 2.1
Name: kuavo-humanoid-sdk-ws
Version: 1.3.1
Summary: A Python SDK for kuavo humanoid robot.
Home-page: https://gitee.com/leju-robot/kuavo-ros-opensource/
Author: ['lejurobot']
Author-email: edu@lejurobot.com
License: MIT
Project-URL: Documentation, https://gitee.com/leju-robot/kuavo-ros-opensource/
Project-URL: Source Code, https://gitee.com/leju-robot/kuavo-ros-opensource/
Keywords: kuavo,humanoid,robot,robotics,lejurobot,ros
Classifier: Development Status :: 4 - Beta
Classifier: Intended Audience :: Developers
Classifier: License :: OSI Approved :: MIT License
Classifier: Operating System :: POSIX :: Linux
Classifier: Programming Language :: Python :: 3
Classifier: Programming Language :: Python :: 3.8
Classifier: Programming Language :: Python :: 3.9
Classifier: Programming Language :: Python :: 3.10
Classifier: Topic :: Software Development :: Libraries :: Python Modules
Requires-Python: >=3.8
Requires-Dist: numpy
Requires-Dist: transitions
Requires-Dist: roslibpy
Requires-Dist: argparse
Requires-Dist: transforms3d
